tagone/__init__.py
tagone/exceptions.py
tagone/utils.py
tagone-0.1.4.dist-info/METADATA
tagone-0.1.4.dist-info/WHEEL
tagone-0.1.4.dist-info/top_level.txt
tagone-0.1.4.dist-info/RECORD
