Metadata-Version: 2.1
Name: tagone
Version: 0.1.4
Summary: TagOne Client
Home-page: UNKNOWN
Author: Junior Vidotti
Author-email: jrvidotti@gmail.com
License: UNKNOWN
Platform: UNKNOWN
Requires-Dist: requests
